{
    "/js/chunks/orders.js": "/js/chunks/orders.js?id=c01fb0323e3ccfaceca1",
    "/js/chunks/pages.js": "/js/chunks/pages.js?id=950110d177f56d4cbd2f",
    "/js/chunks/collections.js": "/js/chunks/collections.js?id=cf910704eabf5225d583",
    "/js/chunks/view-menu.js": "/js/chunks/view-menu.js?id=e7c9569181f2155bc76d",
    "/js/chunks/view-product.js": "/js/chunks/view-product.js?id=10a3ec441b680c28fc05",
    "/js/chunks/collectiontypes.js": "/js/chunks/collectiontypes.js?id=4a5258253720ff444507",
    "/js/chunks/account.js": "/js/chunks/account.js?id=5f2028807760b502862b",
    "/js/chunks/view-product-customisations.js": "/js/chunks/view-product-customisations.js?id=545142963082521afe08",
    "/js/chunks/view-form.js": "/js/chunks/view-form.js?id=a593a82337f760c2dca6",
    "/js/chunks/users.js": "/js/chunks/users.js?id=8387d387a6261ed222fd",
    "/js/chunks/config.js": "/js/chunks/config.js?id=51be4a28beae4a996f8d",
    "/js/chunks/view-user.js": "/js/chunks/view-user.js?id=c8b9b8e129fd6e6ac97f",
    "/js/chunks/import-export.js": "/js/chunks/import-export.js?id=f855c40e37913d6ef717",
    "/js/chunks/quotes.js": "/js/chunks/quotes.js?id=83f6f867fe4b6b66738f",
    "/js/chunks/view-product-variants.js": "/js/chunks/view-product-variants.js?id=4231a57c5812d226249b",
    "/js/chunks/view-product-pricing.js": "/js/chunks/view-product-pricing.js?id=878efba4d3bd79f3a027",
    "/js/chunks/view-product-ordering.js": "/js/chunks/view-product-ordering.js?id=d2f5c39acac82c544445",
    "/js/chunks/view-product-images.js": "/js/chunks/view-product-images.js?id=752ff5ec3b86c0c9eda9",
    "/js/chunks/products.js": "/js/chunks/products.js?id=597128a3e5463e0294e8",
    "/js/chunks/pro-formas.js": "/js/chunks/pro-formas.js?id=b89648937db6a9934fb5",
    "/js/chunks/menus.js": "/js/chunks/menus.js?id=1cfe245e5e9fb1487a94",
    "/js/chunks/galleries.js": "/js/chunks/galleries.js?id=ee05f6c5333ee66f3274",
    "/js/chunks/forms.js": "/js/chunks/forms.js?id=68da055d317b4e07fa32",
    "/js/chunks/view-estimates.js": "/js/chunks/view-estimates.js?id=32d14155a505b3132b8d",
    "/js/chunks/new-estimates.js": "/js/chunks/new-estimates.js?id=00088d844fcd3cda2374",
    "/js/chunks/estimates.js": "/js/chunks/estimates.js?id=ad70319f86b18ec912b1",
    "/js/chunks/customers.js": "/js/chunks/customers.js?id=db1ce9866af7080de74f",
    "/js/chunks/not-found.js": "/js/chunks/not-found.js?id=82c198468974b0ed1401",
    "/js/chunks/dashboard.js": "/js/chunks/dashboard.js?id=e8ce60c1877e64bbc9b8",
    "/js/admin.js": "/js/admin.js?id=81d0a520f874823c9302",
    "/css/admin.css": "/css/admin.css?id=c5dcddb9fad87e045374",
    "/js/vendor.js": "/js/vendor.js?id=00ae855263e2d55fc0f4",
    "/js/chunks/errors.js": "/js/chunks/errors.js?id=f065599f9be53f922cf5",
    "/js/chunks/data-table.js": "/js/chunks/data-table.js?id=4c514680235593d8e921",
    "/js/chunks/file-picker-modal.js": "/js/chunks/file-picker-modal.js?id=ac43d892c6e51a0b999f",
    "/js/chunks/product-page-layout.js": "/js/chunks/product-page-layout.js?id=d52a63093a2a2d925640",
    "/js/chunks/product-table.js": "/js/chunks/product-table.js?id=e7b33f10da596d030af6",
    "/js/chunks/product-form.js": "/js/chunks/product-form.js?id=30c7c00c653f09caa14a",
    "/js/chunks/print-download-button.js": "/js/chunks/print-download-button.js?id=d3845e6f70dcc3e66644",
    "/js/chunks/address-form.js": "/js/chunks/address-form.js?id=b0e59b5536b037b10d33",
    "/js/chunks/galleries-component.js": "/js/chunks/galleries-component.js?id=888f34db03b5fa605cab",
    "/js/chunks/payment-form.js": "/js/chunks/payment-form.js?id=548ced380c1d48610fc8",
    "/js/chunks/customer-information-form.js": "/js/chunks/customer-information-form.js?id=8d97f2e5635c6a492ead",
    "/js/chunks/gallery-component.js": "/js/chunks/gallery-component.js?id=17410fee59637dc92652",
    "/js/chunks/form-field-component.js": "/js/chunks/form-field-component.js?id=ca89b1d13f38ae9d6eca",
    "/js/chunks/file-upload-component.js": "/js/chunks/file-upload-component.js?id=f225dcbd10502075f141",
    "/js/chunks/page-layout.js": "/js/chunks/page-layout.js?id=f5526ca9b19ad443a9b9",
    "/js/chunks/product-variant-component.js": "/js/chunks/product-variant-component.js?id=9a4e31e7a48ea4134f74",
    "/js/chunks/product-customisation-option-component.js": "/js/chunks/product-customisation-option-component.js?id=eecf603504d540ed76aa",
    "/js/chunks/product-customisation-component.js": "/js/chunks/product-customisation-component.js?id=ac2fce623ddaa1679281",
    "/js/chunks/payment-details.js": "/js/chunks/payment-details.js?id=ad8c6e7922cbf7cb6e4a",
    "/js/chunks/form-section-component.js": "/js/chunks/form-section-component.js?id=9ce8f966571c3b956c8e",
    "/js/chunks/card-payment-form.js": "/js/chunks/card-payment-form.js?id=31b10efa620f57362ef9",
    "/js/manifest.js": "/js/manifest.js?id=3a6a5d08c60a39b5efbb",
    "/css/reset.css": "/css/reset.css?id=8c6eee6b2107ef25dc48"
}