{
    "/js/chunks/orders.js": "/js/chunks/orders.js?id=9e9a496f6ab5f8f8ba9b",
    "/js/chunks/pages.js": "/js/chunks/pages.js?id=570fa606cd7a506fc6a1",
    "/js/chunks/products.js": "/js/chunks/products.js?id=6faa8bd0b72da0883b74",
    "/js/chunks/collections.js": "/js/chunks/collections.js?id=bbf06468e68b24f558a2",
    "/js/chunks/collectiontypes.js": "/js/chunks/collectiontypes.js?id=03855d8961c29235dc58",
    "/js/chunks/account.js": "/js/chunks/account.js?id=453748073f36fbcfd288",
    "/js/chunks/users.js": "/js/chunks/users.js?id=34406fbd5c5222dd4e09",
    "/js/chunks/config.js": "/js/chunks/config.js?id=e00f4bb83083ca6732f6",
    "/js/chunks/galleries.js": "/js/chunks/galleries.js?id=c3de7c4789195b782bc7",
    "/js/chunks/not-found.js": "/js/chunks/not-found.js?id=b68957bc89dab60bfbb5",
    "/js/chunks/dashboard.js": "/js/chunks/dashboard.js?id=1c5f48bb8ebdfbe40f09",
    "/js/admin.js": "/js/admin.js?id=facc590734b58cc5c0cd",
    "/css/admin.css": "/css/admin.css?id=db8d811414d0b2edf946",
    "/css/normalize.css": "/css/normalize.css?id=8c6eee6b2107ef25dc48",
    "/js/chunks/view-product.js": "/js/chunks/view-product.js?id=d6a460404ca697baca68",
    "/js/chunks/view-product-variants.js": "/js/chunks/view-product-variants.js?id=14d18ce2e078365cfc6c",
    "/js/chunks/view-product-pricing.js": "/js/chunks/view-product-pricing.js?id=ac5bddb80d44de7ab3cc",
    "/js/chunks/view-product-images.js": "/js/chunks/view-product-images.js?id=05061fb60e4bcbb111c9",
    "/js/chunks/view-product-customisations.js": "/js/chunks/view-product-customisations.js?id=f3e3187e1625ce126c48"
}